{
    "gurobi": {
        "time": 31,
        "optimal": true,
        "obj": 236.0,
        "sol": [
            [
                0,
                4,
                11
            ],
            [
                3
            ],
            [
                12
            ],
            [
                9
            ],
            [
                5,
                8
            ],
            [
                2
            ],
            [
                1
            ],
            [
                6
            ],
            [
                7
            ],
            [
                10
            ]
        ]
    }
}